README.txt
setup.py
newspider/__init__.py
newspider/interfaces.py
newspider/spider.py
newspider.egg-info/PKG-INFO
newspider.egg-info/SOURCES.txt
newspider.egg-info/dependency_links.txt
newspider.egg-info/requires.txt
newspider.egg-info/top_level.txt
newspider.egg-info/zip-safe
newspider/comm/__init__.py
newspider/comm/guarder.py
newspider/comm/req.py
newspider/comm/urlrecoder.py
newspider/comm/utils.py
test/test_classname.py
test/test_invalid_encoding.py
test/test_sohu.py
test/test_threadpool.py