Metadata-Version: 1.1
Name: newspider
Version: 0.9.9
Summary: 分类扒数据的简易框架
Home-page: http://www.typechodev.com
Author: Ray
Author-email: miuyin@126.com
License: MIT
Platform: any
Classifier: License :: OSI Approved :: MIT License
Classifier: Programming Language :: Python
Classifier: Intended Audience :: Developers
Classifier: Operating System :: OS Independent
